render_me_harder/__init__.py
render_me_harder/render_me_harder.py
render_me_harder-0.1.0.dist-info/LICENSE
render_me_harder-0.1.0.dist-info/METADATA
render_me_harder-0.1.0.dist-info/WHEEL
render_me_harder-0.1.0.dist-info/top_level.txt
render_me_harder-0.1.0.dist-info/RECORD
