Metadata-Version: 2.1
Name: render-me-harder
Version: 0.1.0
Summary: Stupidly simple API for rendering 3D models to images
Home-page: https://github.com/minexew/render_me_harder
Author: minexew
Author-email: minexew@gmail.com
License: MIT license
Keywords: render_me_harder
Platform: UNKNOWN
Classifier: Development Status :: 2 - Pre-Alpha
Classifier: Intended Audience :: Developers
Classifier: License :: OSI Approved :: MIT License
Classifier: Natural Language :: English
Classifier: Programming Language :: Python :: 3
Classifier: Programming Language :: Python :: 3.6
Classifier: Programming Language :: Python :: 3.7
Classifier: Programming Language :: Python :: 3.8
Requires-Python: >=3.6
License-File: LICENSE
Requires-Dist: numpy
Requires-Dist: Pillow
Requires-Dist: pyrender
Requires-Dist: trimesh
